matplotlibXtns/__init__.py
matplotlibXtns/cartopyXtns.py
matplotlibXtns/matplotlibXtns.py
matplotlibXtns-20.5.dist-info/LICENSE.txt
matplotlibXtns-20.5.dist-info/METADATA
matplotlibXtns-20.5.dist-info/WHEEL
matplotlibXtns-20.5.dist-info/top_level.txt
matplotlibXtns-20.5.dist-info/RECORD
