Metadata-Version: 2.1
Name: matplotlibXtns
Version: 20.5
Summary: matplotlib extension functions.
Home-page: https://github.com/mommebutenschoen/matplotlibXtns
Author: Momme Butenschön
Author-email: mommebu@yahoo.de
License: GPL
Keywords: matplotlib,numpy,scipy,netCDF4
Platform: UNKNOWN
Classifier: Development Status :: 4 - Beta
Classifier: Intended Audience :: Science/Research
Classifier: Topic :: Software Development :: Libraries :: Python Modules
Classifier: License :: OSI Approved :: GNU General Public License (GPL)
Classifier: Programming Language :: Python :: 2
Classifier: Programming Language :: Python :: 2.6
Classifier: Programming Language :: Python :: 2.7
Classifier: Programming Language :: Python :: 3
Classifier: Programming Language :: Python :: 3.3
Classifier: Programming Language :: Python :: 3.4
Classifier: Programming Language :: Python :: 3.5
Classifier: Programming Language :: Python :: 3.6
Classifier: Programming Language :: Python :: 3.7
Provides-Extra: geographic distances
Provides-Extra: geographic mapping
